LICENSE
README.md
setup.py
FLUID_project_upprpo.egg-info/PKG-INFO
FLUID_project_upprpo.egg-info/SOURCES.txt
FLUID_project_upprpo.egg-info/dependency_links.txt
FLUID_project_upprpo.egg-info/requires.txt
FLUID_project_upprpo.egg-info/top_level.txt
fluid_simulation/Interface.py
fluid_simulation/Properties.py
fluid_simulation/__init__.py
fluid_simulation/Simulation/Calculations.py
fluid_simulation/Simulation/FluidCube.py
fluid_simulation/Simulation/__init__.py