Metadata-Version: 2.1
Name: FLUID-project-upprpo
Version: 1.1.1
Home-page: https://github.com/AxeVal/Fluid
Author: VeLoR
Author-email: 
Keywords: pypi,cicd,python
Classifier: Programming Language :: Python :: 3
Classifier: Operating System :: Microsoft :: Windows
License-File: LICENSE
